osm/__init__.py
osm/admin.py
osm/apps.py
osm/models.py
osm/route_db.py
osm/tasks.py
osm/urls.py
osm/views.py
osm/api/__init__.py
osm/api/filters.py
osm/api/serializers.py
osm/api/urls.py
osm/api/views.py
osm/management/__init__.py
osm/management/commands/__init__.py
osm/management/commands/countries.py
osm/management/commands/osm.py
osm/migrations/0001_initial.py
osm/migrations/__init__.py
osm/static/css/osm.css
osm/static/js/osm.js
osm/templates/osm/base.html
osm/test_utils/__init__.py
django_osm-0.1.0.dist-info/AUTHORS.rst
django_osm-0.1.0.dist-info/LICENSE
django_osm-0.1.0.dist-info/METADATA
django_osm-0.1.0.dist-info/WHEEL
django_osm-0.1.0.dist-info/top_level.txt
django_osm-0.1.0.dist-info/RECORD
