Metadata-Version: 2.1
Name: django-osm
Version: 0.1.0
Summary: Project Open Street Map management
Home-page: https://github.com/dcopm999/django-osm
Author: Pavel Tanchev
Author-email: dcopm999@gmail.com
License: MIT
Keywords: django-osm
Platform: UNKNOWN
Classifier: Development Status :: 3 - Alpha
Classifier: Framework :: Django :: 2.1
Classifier: Intended Audience :: Developers
Classifier: License :: OSI Approved :: BSD License
Classifier: Natural Language :: English
Classifier: Programming Language :: Python :: 2
Classifier: Programming Language :: Python :: 2.7
Classifier: Programming Language :: Python :: 3
Classifier: Programming Language :: Python :: 3.5
Classifier: Programming Language :: Python :: 3.6
Requires-Dist: celery (==5.1.2)
Requires-Dist: django-filter (==2.4.0)
Requires-Dist: djangorestframework-gis (==0.17)
Requires-Dist: djangorestframework (==3.12.4)
Requires-Dist: wget (==3.2)
